Workbook

Sheet sozluk
A1: ability | B1: Ebılıti | C1: hüner [i.] | D1: kabiliyet [i.] | E1: yetenek [i.] | F1: A1 | K1: 531
A2: able | B2: Eybıl | C2: hünerli [s.] | D2: kadir [s.] | E2: gücü yeten [s.] | F2: A1
A3: abroad | B3: Ebrod | C3: yurt dışında [zf.] | D3: gurbet [i.] | E3: yurt dışı [i.] | F3: A1
A4: accept | B4: Eksept | C4: kabullenmek [f.] | D4: kabul etmek [f.] | E4: almak [f.] | F4: A1
A5: accident | B5: Eksidınt | C5: rastlantı [i.] | D5: kaza [i.] | E5: beklenmedik olay [i.] | F5: A1
A6: according to | B6: Ekording Tu | C6: göre [ed.] | D6: uyarınca [ed.] | E6: üzere [ed.] | F6: A1
A7: achieve | B7: Açiv | C7: elde etmek [f.] | D7: başarmak [f.] | E7: ulaşmak [f.] | F7: A1
A8: act | B8: Ekt | C8: davranmak [f.] | D8: hareket etmek [f.] | E8: eylem [i.] | F8: A1
A9: active | B9: Ektiv | C9: faal [s.] | D9: aktif [s.] | E9: etkin [s.] | F9: A1
A10: actually | B10: Ekçueli | C10: fiilen [zf.] | D10: aslında [zf.] | E10: hem [zf.] | F10: A1
A11: adult | B11: Edalt | C11: yetişkin [i.] | D11: er kişi [i.] | E11: yetişkin kişi [i.] | F11: A1
A12: advantage | B12: Edventıc | C12: avantaj [i.] | D12: fayda [i.] | E12: yarar [i.] | F12: A1
A13: adventure | B13: Edvençur | C13: macera [i.] | D13: serüven [i.] | E13: atılmak [f.] | F13: A1
... A41: anywhere | B41: Eniveır | C41: nerede olursa olsun [zf.] | D41: herhangi bir yer [zf.] | E41: herhangi bir yerde [zf.] | F41: A1
A42: app | B42: Ep | C42: uygulama | F42: A1
A43: appear | B43: Eppiır | C43: belli olmak [f.] | D43: görünmek [f.] | E43: belirmek [f.] | F43: A1
A44: appearance | B44: Eppiırıns | C44: dış görünüş [i.] | D44: görünüm [i.] | E44: görünüş [i.] | F44: A1
A45: apply | B45: Eplay | C45: uygulamak [f.] | D45: başvurmak [f.] | E45: müracaat etmek [f.] | F45: A1
A46: architect | B46: Arkitekt | C46: mimar [i.] | D46: yapmak [f.] | E46: tasarlamak [f.] | F46: A1
A47: architecture | B47: Arkitekçır | C47: mimarlık [i.] | D47: inşaat [i.] | E47: yapı [i.] | F47: A1
A48: argue | B48: Argüu | C48: tartışmak [f.] | D48: çekişmek [f.] | E48: göstergesi olmak [f.] | F48: A1
A49: argument | B49: Argümınt | C49: argüman [i.] | D49: tartışma [i.] | E49: sav [i.] | F49: A1
A50: army | B50: Armi | C50: ordu [i.] | D50: kalabalık [i.] | E50: topluluk [i.] | F50: A1
A51: arrange | B51: Ereync | C51: ayarlamak [f.] | D51: düzenlemek [f.] | E51: hazırlanmak [f.] | F51: A1
A52: arrangement | B52: Ereyncmınt | C52: ayarlama [i.] | D52: aranjman [i.] | E52: düzenleme [i.] | F52: A1
A53: as | B53: Ez | C53: olarak [zf.] | D53: gibi [ed.] | E53: dahi [zf.] | F53: A1
A54: asleep | B54: Esliip | C54: uyuyan [s.] | D54: tembel [s.] | E54: uyuşuk [s.] | F54: A1
... A87: between | B87: bitvin | C87: arasında [zf.] | D87: arasına [zf.] | E87: ortada [zf.] | F87: A1
A88: billion | B88: Bilyın | C88: milyar [i.] | D88: bilyon [i.] | F88: A1
A89: bin | B89: Bin | C89: çöp kutusu [i.] | D89: ambarlamak [f.] | E89: çöpe atmak [f.] | F89: A1
A90: biology | B90: Bayoloci | C90: dirimbilim [i.] | D90: yaşambilim [i.] | E90: biyoloji [i.] | F90: A1
A91: birth | B91: Börth | C91: doğum [i.] | D91: kaynak [i.] | E91: doğum [i.] | F91: A1
A92: biscuit | B92: Biskit | C92: bisküvi [i.] | D92: gevrek [i.] | E92: bisküvi [i.] | F92: A1
A93: bit | B93: Bit | C93: gem [i.] | D93: gemlemek [f.] | E93: ikili savmak [f.] | F93: A1
A94: blank | B94: Blenk | C94: boşluk [i.] | D94: boş [s.] | E94: silmek [f.] | F94: A1
A95: blood | B95: Blad | C95: kan [i.] | D95: kan bağı [i.] | E95: dem [i.] | F95: A1
A96: blow | B96: Blou | C96: esmek [f.] | D96: üflemek [f.] | E96: darbe [i.] | F96: A1
A97: board | B97: Boord | C97: binmek [f.] | D97: tahta döşemek [f.] | E97: kurul [i.] | F97: A1
A98: boil | B98: Boıl | C98: haşlamak [f.] | D98: kaynamak [f.] | E98: çıban [i.] | F98: A1
A99: bone | B99: Boun | C99: kılçık [i.] | D99: kemik [i.] | E99: kılçıklarını ayıklamak (balık) [f.] | F99: A1
A100: book | B100: Buk | C100: ayırtmak [f.] | D100: kitap [i.] | E100: deftere işlemek [f.] | F100: A1
... A374: hit | B374: Hit | C374: çarpmak [f.] | D374: vurmak [f.] | E374: isabet etmek [f.] | F374: A1
A375: hockey | B375: Haki | C375: hokey [i.] | D375: hokey | F375: A1
A376: hold | B376: Hold | C376: sahip olmak [f.] | D376: zaptetmek [f.] | E376: düzenlemek [f.] | F376: A1
A377: hole | B377: Hol | C377: çukur [i.] | D377: delik [i.] | E377: kapanmak [f.] | F377: A1
A378: home | B378: Hom | C378: ev [i.] | D378: yerleştirmek [f.] | E378: yuvasına dönmek [f.] | F378: A1
A379: hope | B379: Houp | C379: ummak [f.] | D379: umut etmek [f.] | E379: ümit etmek [f.] | F379: A1
A380: huge | B380: Hüc | C380: iri [s.] | D380: kocaman [s.] | E380: devasa [s.] | F380: A1
A381: human | B381: Hüman | C381: insan [i.] | D381: insani [s.] | E381: insanlık [i.] | F381: A1
A382: hurt | B382: Hört | C382: acımak [f.] | D382: incitmek [f.] | E382: yaralamak [f.] | F382: A1
A383: ideal | B383: Aydil | C383: ülkü [i.] | D383: ideal [s.] | E383: mefkure [i.] | F383: A1
A384: identify | B384: Aydentifay | C384: tanımlamak [f.] | D384: tanımak [f.] | E384: kimliğini saptamak [f.] | F384: A1
A385: ill | B385: İl | C385: hasta [s.] | D385: fenalık [i.] | E385: kötülük [i.] | F385: A1
A386: illness | B386: İlnes | C386: hastalık [i.] | D386: maraz [i.] | E386: illet [i.] | F386: A1
A387: image | B387: İmic | C387: şekil [i.] | D387: imge [i.] | E387: imaj [i.] | F387: A1
... A427: knowledge | B427: Navlıc | C427: bilgi [i.] | D427: ilim [i.] | E427: bili [i.] | F427: A1
A428: lab | B428: Leb | C428: laboratuvar [i.] | D428: labrador retriever (köpek) [i.] | F428: A1
A429: lady | B429: Leydi | C429: bayan [i.] | D429: hanımefendi [i.] | E429: hatun [i.] | F429: A1
A430: lake | B430: Leyk | C430: göl [i.] | D430: göl [i.] | E430: koyu kırmızı boya [i.] | F430: A1
A431: lamp | B431: Lemp | C431: ampul [i.] | D431: lamba [i.] | E431: kandil [i.] | F431: A1
A432: land | B432: Lend | C432: karaya ayak basmak [f.] | D432: kıyıya çıkmak [f.] | E432: karaya çıkmak [f.] | F432: A1
A433: laptop | B433: Laptop | C433: dizüstü bilgisayar [i.] | D433: dizüstü [i.] | E433: dizüstü bilgisayarı | F433: A1
A434: last | B434: Lest | C434: sonuncu [s.] | D434: son [s.] | E434: tutunmak [f.] | F434: A1
A435: later | B435: Leytır | C435: sonradan [zf.] | D435: sonra [zf.] | E435: sonraki [zf.] | F435: A1
A436: laughter | B436: Laftır | C436: kahkaha [i.] | D436: kahkahalar [i.] | E436: hande [i.] | F436: A1
A437: law | B437: Lou | C437: yasa [i.] | D437: hukuk [i.] | E437: kanun [i.] | F437: A1
A438: lawyer | B438: Louyır | C438: avukat [i.] | D438: hukukçu [i.] | E438: dava vekili [i.] | F438: A1
A439: lazy | B439: Leyzi | C439: uyuşuk [s.] | D439: miskin [s.] | E439: tembel [s.] | F439: A1
A440: lead | B440: Led | C440: yol göstermek [f.] | D440: rehberlik etmek [f.] | E440: sürmek [f.] | F440: A1
... A552: per | B552: pör | C552: her [zf.] | D552: beher [zf.] | E552: rücuen [zf.] | F552: A1
A553: per cent | B553: Pır sent | C553: yüzde [i.] | D553: yüzde | F553: A1
A554: perform | B554: Pörform | C554: rol yapmak [f.] | D554: yapmak [f.] | E554: yerine getirmek [f.] | F554: A1
A555: perhaps | B555: Pörheps | C555: belki [ünl.] | D555: muhtemelen [zf.] | E555: bir ihtimal [zf.] | F555: A1
A556: permission | B556: Pörmişn | C556: müsaade [i.] | D556: izin [i.] | E556: destur [i.] | F556: A1
A557: personality | B557: Pörsınelıti | C557: kişilik [i.] | D557: şahsiyet [i.] | E557: önemli kişi [i.] | F557: A1
A558: pet | B558: Pet | C558: evde beslenen hayvan [i.] | D558: ev hayvanı [i.] | E558: evcil hayvan [i.] | F558: A1
A559: petrol | B559: Petrıl | C559: petrol [i.] | D559: benzin [i.] | E559: benzin | F559: A1
A560: photograph | B560: Fotıgraf | C560: fotoğraflamak [f.] | D560: fotoğrafını çekmek [f.] | E560: resim vermek [f.] | F560: A1
A561: physical | B561: Fizikıl | C561: bedensel [s.] | D561: muayene [i.] | E561: bedeni [s.] | F561: A1
A562: physics | B562: Fiziks | C562: fizik [i.] | D562: fizik (bilim) | E562: fiziksel | F562: A1
A563: pick | B563: Pik | C563: seçmek [f.] | D563: pena [i.] | E563: gitar penası [i.] | F563: A1
A564: pilot | B564: Paylıt | C564: pilot [i.] | D564: pilotluk yapmak [f.] | E564: yol göstermek [f.] | F564: A1
A565: planet | B565: Plenıt | C565: gezegen [i.] | D565: seyyare [i.] | E565: gezegen | F565: A1
... A669: save | B669: seyv | C669: (para) biriktirmek [f.] | D669: kurtarmak [f.] | E669: biriktirmek [f.] | F669: A1
A670: scared | B670: Skeyrd | C670: korkmuş [s.] | F670: A1
A671: scary | B671: Skeri | C671: ürkütücü [s.] | D671: korkunç [s.] | E671: korkutucu [s.] | F671: A1
A672: scene | B672: Sin | C672: sahne [i.] | D672: manzara [i.] | E672: olay yeri [i.] | F672: A1
A673: schedule | B673: Skecul | C673: plan [i.] | D673: program [i.] | E673: tarifeye geçirmek [f.] | F673: A1
A674: score | B674: Skoor | C674: puan [i.] | D674: skor [i.] | E674: hesaplaşmak [f.] | F674: A1
A675: screen | B675: Skriin | C675: ekran [i.] | D675: göstermek [f.] | E675: siper etmek [f.] | F675: A1
A676: search | B676: Sörç | C676: araştırmak [f.] | D676: aramak [f.] | E676: araştırma [i.] | F676: A1
A677: season | B677: Siizn | C677: sezon [i.] | D677: mevsim [i.] | E677: baharatını katmak [f.] | F677: A1
A678: seat | B678: Siit | C678: oturtmak [f.] | D678: koltuk [i.] | E678: oturacak yer [i.] | F678: A1
A679: secondly | B679: Sekındli | C679: saniyen [zf.] | D679: ikinci olarak [zf.] | F679: A1
A680: secret | B680: Sikrıt | C680: sır [i.] | D680: gizli [s.] | E680: gizem [i.] | F680: A1
A681: secretary | B681: Sekrıtri | C681: sekreter [i.] | D681: yazman [i.] | E681: yazı masası [i.] | F681: A1
A682: seem | B682: Siim | C682: gözükmek [f.] | D682: görünmek [f.] | E682: görünmek [f.] | F682: A1
A683: sense | B683: Sens | C683: algılamak [f.] | D683: hissetmek [f.] | E683: algı [i.] | F683: A1
A684: separate | B684: Seprıt | C684: ayırmak [f.] | D684: ayrı [s.] | E684: ayrıştırmak [f.] | F684: A1
A685: series | B685: Siriz | C685: seri [i.] | D685: dizi [i.] | E685: zincir [i.] | F685: A1
...

Sheet tum kelimeler
A1: Kelime | B1: Frekans | C1: türkçe_okunuş | F1: anlam1 | G1: anlam2 | H1: anlam3 | I1: seviye
A2: about | B2: 469 | C2: Ebaut | D2: =IF(C2<>"",C2,VLOOKUP(A2,Sayfa2!$A$1:$C$9998,2,FALSE)) -> Ebaut | E2: =IF(C2<>"",F2,VLOOKUP(A2,Sayfa2!$A$1:$C$9998,3,FALSE)) -> hemen hemen [zf.] | F2: hemen hemen [zf.] | G2: aşağı yukarı [zf.] | H2: yaklaşık [zf.] | I2: A2
A3: up | B3: 456 | C3: Ap | D3: =IF(C3<>"",C3,VLOOKUP(A3,Sayfa2!$A$1:$C$9998,2,FALSE)) -> Ap | E3: =IF(C3<>"",F3,VLOOKUP(A3,Sayfa2!$A$1:$C$9998,3,FALSE)) -> yukarı [ünl.] | F3: yukarı [ünl.] | G3: yükseltmek [f.] | H3: artırmak [f.] | I3: A2
A4: but | B4: 454 | C4: Bat | D4: =IF(C4<>"",C4,VLOOKUP(A4,Sayfa2!$A$1:$C$9998,2,FALSE)) -> Bat | E4: =IF(C4<>"",F4,VLOOKUP(A4,Sayfa2!$A$1:$C$9998,3,FALSE)) -> ancak [bağ.] | F4: ancak [bağ.] | G4: fakat [bağ.] | H4: itiraz [i.] | I4: A2
A5: get | B5: 428 | C5: Get | D5: =IF(C5<>"",C5,VLOOKUP(A5,Sayfa2!$A$1:$C$9998,2,FALSE)) -> Get | E5: =IF(C5<>"",F5,VLOOKUP(A5,Sayfa2!$A$1:$C$9998,3,FALSE)) -> elde etmek [f.] | F5: elde etmek [f.] | G5: almak [f.] | H5: kazanmak [f.] | I5: A2
A6: her | B6: 420 | C6: Hör | D6: =IF(C6<>"",C6,VLOOKUP(A6,Sayfa2!$A$1:$C$9998,2,FALSE)) -> Hör | E6: =IF(C6<>"",F6,VLOOKUP(A6,Sayfa2!$A$1:$C$9998,3,FALSE)) -> ona [zm.] | F6: ona [zm.] | G6: dişil onu [zm.] | H6: ondan [zm.] | I6: A2
A7: like | B7: 416 | C7: layk | D7: =IF(C7<>"",C7,VLOOKUP(A7,Sayfa2!$A$1:$C$9998,2,FALSE)) -> layk | E7: =IF(C7<>"",F7,VLOOKUP(A7,Sayfa2!$A$1:$C$9998,3,FALSE)) -> beğenmek [f.] | F7: beğenmek [f.] | G7: hoşlanmak [f.] | H7: sevmek [f.] | I7: A2
A8: from | B8: 387 | C8: from | D8: =IF(C8<>"",C8,VLOOKUP(A8,Sayfa2!$A$1:$C$9998,2,FALSE)) -> from | E8: =IF(C8<>"",F8,VLOOKUP(A8,Sayfa2!$A$1:$C$9998,3,FALSE)) -> itibaren [ed.] | F8: itibaren [ed.] | G8: -den beri [ed.] | H8: -den [ed.] | I8: A2
A9: time | B9: 385 | C9: Taym | D9: =IF(C9<>"",C9,VLOOKUP(A9,Sayfa2!$A$1:$C$9998,2,FALSE)) -> Taym | E9: =IF(C9<>"",F9,VLOOKUP(A9,Sayfa2!$A$1:$C$9998,3,FALSE)) -> kez [i.] | F9: kez [i.] | G9: kere [i.] | H9: müddet [i.] | I9: A2
A10: had | B10: 383 | C10: Hed | D10: =IF(C10<>"",C10,VLOOKUP(A10,Sayfa2!$A$1:$C$9998,2,FALSE)) -> Hed | E10: =IF(C10<>"",F10,VLOOKUP(A10,Sayfa2!$A$1:$C$9998,3,FALSE)) -> 0 | F10: 0
A11: when | B11: 383 | C11: Wen | D11: =IF(C11<>"",C11,VLOOKUP(A11,Sayfa2!$A$1:$C$9998,2,FALSE)) -> Wen | E11: =IF(C11<>"",F11,VLOOKUP(A11,Sayfa2!$A$1:$C$9998,3,FALSE)) -> ne zaman [zf.] | F11: ne zaman [zf.] | G11: zaman [i.] | H11: ne vakit [zf.] | I11: A2
A12: how | B12: 379 | C12: Haw | D12: =IF(C12<>"",C12,VLOOKUP(A12,Sayfa2!$A$1:$C$9998,2,FALSE)) -> Haw | E12: =IF(C12<>"",F12,VLOOKUP(A12,Sayfa2!$A$1:$C$9998,3,FALSE)) -> nasıl [zf.] | F12: nasıl [zf.] | G12: yapma yöntemi [i.] | H12: yapma tarzı [i.] | I12: A2
A13: there | B13: 371 | C13: Theer | D13: =IF(C13<>"",C13,VLOOKUP(A13,Sayfa2!$A$1:$C$9998,2,FALSE)) -> Theer | E13: =IF(C13<>"",F13,VLOOKUP(A13,Sayfa2!$A$1:$C$9998,3,FALSE)) -> oraya [zf.] | F13: oraya [zf.] | G13: orada [zf.] | H13: ora [zf.] | I13: A2
A14: out | B14: 359 | C14: Aut | D14: =IF(C14<>"",C14,VLOOKUP(A14,Sayfa2!$A$1:$C$9998,2,FALSE)) -> Aut | E14: =IF(C14<>"",F14,VLOOKUP(A14,Sayfa2!$A$1:$C$9998,3,FALSE)) -> çıkış [i.] | F14: çıkış [i.] | G14: dışarıda [zf.] | H14: dışarı [zf.] | I14: A2
A15: by | B15: 354 | C15: bay | D15: =IF(C15<>"",C15,VLOOKUP(A15,Sayfa2!$A$1:$C$9998,2,FALSE)) -> bay | E15: =IF(C15<>"",F15,VLOOKUP(A15,Sayfa2!$A$1:$C$9998,3,FALSE)) -> geçecek biçimde [zf.] | F15: geçecek biçimde [zf.] | G15: yakın [zf.] | H15: evde [zf.] | I15: A2
A16: people | B16: 354 | C16: Piipl | D16: =IF(C16<>"",C16,VLOOKUP(A16,Sayfa2!$A$1:$C$9998,2,FALSE)) -> Piipl | E16: =IF(C16<>"",F16,VLOOKUP(A16,Sayfa2!$A$1:$C$9998,3,FALSE)) -> insanlar [i.] | F16: insanlar [i.] | G16: ulus [i.] | H16: halk [i.] | I16: A2
A17: would | B17: 348 | C17: Vud | D17: =IF(C17<>"",C17,VLOOKUP(A17,Sayfa2!$A$1:$C$9998,2,FALSE)) -> Vud | E17: =IF(C17<>"",F17,VLOOKUP(A17,Sayfa2!$A$1:$C$9998,3,FALSE)) -> istemek [f.] | F17: istemek [f.] | G17: -ecekti [f.] | H17: -çekti [f.] | I17: A2
A18: more | B18: 339 | C18: Mor | D18: =IF(C18<>"",C18,VLOOKUP(A18,Sayfa2!$A$1:$C$9998,2,FALSE)) -> Mor | E18: =IF(C18<>"",F18,VLOOKUP(A18,Sayfa2!$A$1:$C$9998,3,FALSE)) -> daha fazla [s.] | F18: daha fazla [s.] | G18: daha [zf.] | H18: fazla şey [i.] | I18: A2
A19: all | B19: 335 | C19: Ol | D19: =IF(C19<>"",C19,VLOOKUP(A19,Sayfa2!$A$1:$C$9998,2,FALSE)) -> Ol | E19: =IF(C19<>"",F19,VLOOKUP(A19,Sayfa2!$A$1:$C$9998,3,FALSE)) -> tüm [i.] | F19: tüm [i.] | G19: bütün [i.] | H19: hepsi [zm.] | I19: A1
A20: go | B20: 314 | C20: Go | D20: =IF(C20<>"",C20,VLOOKUP(A20,Sayfa2!$A$1:$C$9998,2,FALSE)) -> Go | E20: =IF(C20<>"",F20,VLOOKUP(A20,Sayfa2!$A$1:$C$9998,3,FALSE)) -> hareket etmek [f.] | F20: hareket etmek [f.] | G20: gitmek [f.] | H20: went - gone [f.] | I20: A2
A21: their | B21: 298 | C21: Theır | D21: =IF(C21<>"",C21,VLOOKUP(A21,Sayfa2!$A$1:$C$9998,2,FALSE)) -> Theır | E21: =IF(C21<>"",F21,VLOOKUP(A21,Sayfa2!$A$1:$C$9998,3,FALSE)) -> onların [zm.] | F21: onların [zm.] | G21: 0 | H21: 0 | I21: A2
A22: our | B22: 296 | C22: Aar | D22: =IF(C22<>"",C22,VLOOKUP(A22,Sayfa2!$A$1:$C$9998,2,FALSE)) -> Aar | E22: =IF(C22<>"",F22,VLOOKUP(A22,Sayfa2!$A$1:$C$9998,3,FALSE)) -> bizim [zm.] | F22: bizim [zm.] | G22: bizim [zm.] | H22: 0 | I22: A2
A23: just | B23: 282 | C23: Cast | D23: =IF(C23<>"",C23,VLOOKUP(A23,Sayfa2!$A$1:$C$9998,2,FALSE)) -> Cast | E23: =IF(C23<>"",F23,VLOOKUP(A23,Sayfa2!$A$1:$C$9998,3,FALSE)) -> sadece [s.] | F23: sadece [s.] | G23: adil [s.] | H23: yalnızca [zf.] | I23: A2
A24: his | B24: 278 | C24: Hiz | D24: =IF(C24<>"",C24,VLOOKUP(A24,Sayfa2!$A$1:$C$9998,2,FALSE)) -> Hiz | E24: =IF(C24<>"",F24,VLOOKUP(A24,Sayfa2!$A$1:$C$9998,3,FALSE)) -> eril onunki [zm.] | F24: eril onunki [zm.] | G24: onun [zm.] | H24: onunki [zm.] | I24: A1
A25: need | B25: 264 | C25: Niid | D25: =IF(C25<>"",C25,VLOOKUP(A25,Sayfa2!$A$1:$C$9998,2,FALSE)) -> Niid | E25: =IF(C25<>"",F25,VLOOKUP(A25,Sayfa2!$A$1:$C$9998,3,FALSE)) -> ihtiyaç duymak [f.] | F25: ihtiyaç duymak [f.] | G25: gerek [i.] | H25: gereksinim [i.] | I25: A1
A26: some | B26: 259 | C26: Sam | D26: =IF(C26<>"",C26,VLOOKUP(A26,Sayfa2!$A$1:$C$9998,2,FALSE)) -> Sam | E26: =IF(C26<>"",F26,VLOOKUP(A26,Sayfa2!$A$1:$C$9998,3,FALSE)) -> biraz [s.] | F26: biraz [s.] | G26: bazı [s.] | H26: birkaç [s.] | I26: A2
A27: work | B27: 246 | C27: Wörk | D27: =IF(C27<>"",C27,VLOOKUP(A27,Sayfa2!$A$1:$C$9998,2,FALSE)) -> Wörk | E27: =IF(C27<>"",F27,VLOOKUP(A27,Sayfa2!$A$1:$C$9998,3,FALSE)) -> çalışmak [f.] | F27: çalışmak [f.] | G27: işe yaramak [f.] | H27: iş yapmak [f.] | I27: A2
A28: or | B28: 231 | C28: Or | D28: =IF(C28<>"",C28,VLOOKUP(A28,Sayfa2!$A$1:$C$9998,2,FALSE)) -> Or | E28: =IF(C28<>"",F28,VLOOKUP(A28,Sayfa2!$A$1:$C$9998,3,FALSE)) -> ya da [bağ.] | F28: ya da [bağ.] | G28: veya [bağ.] | H28: altın sarısı [i.] | I28: A2
A29: should | B29: 226 | C29: Şud | D29: =IF(C29<>"",C29,VLOOKUP(A29,Sayfa2!$A$1:$C$9998,2,FALSE)) -> Şud | E29: =IF(C29<>"",F29,VLOOKUP(A29,Sayfa2!$A$1:$C$9998,3,FALSE)) -> gerekmek [f.] | F29: gerekmek [f.] | G29: -malı [f.] | H29: -meli [f.] | I29: A2
A30: know | B30: 224 | C30: Nou | D30: =IF(C30<>"",C30,VLOOKUP(A30,Sayfa2!$A$1:$C$9998,2,FALSE)) -> Nou | E30: =IF(C30<>"",F30,VLOOKUP(A30,Sayfa2!$A$1:$C$9998,3,FALSE)) -> bilmek [f.] | F30: bilmek [f.] | G30: tanımak [f.] | H30: knew - known [f.] | I30: A2
A31: see | B31: 224 | C31: Sii | D31: =IF(C31<>"",C31,VLOOKUP(A31,Sayfa2!$A$1:$C$9998,2,FALSE)) -> Sii | E31: =IF(C31<>"",F31,VLOOKUP(A31,Sayfa2!$A$1:$C$9998,3,FALSE)) -> görmek [f.] | F31: görmek [f.] | G31: bakmak [f.] | H31: saw - seen [f.] | I31: A2
A32: here | B32: 221 | C32: Hiır | D32: =IF(C32<>"",C32,VLOOKUP(A32,Sayfa2!$A$1:$C$9998,2,FALSE)) -> Hiır | E32: =IF(C32<>"",F32,VLOOKUP(A32,Sayfa2!$A$1:$C$9998,3,FALSE)) -> burada [zf.] | F32: burada [zf.] | G32: buraya [zf.] | H32: burda [zf.] | I32: A2
A33: new | B33: 220 | C33: Nuu | D33: =IF(C33<>"",C33,VLOOKUP(A33,Sayfa2!$A$1:$C$9998,2,FALSE)) -> Nuu | E33: =IF(C33<>"",F33,VLOOKUP(A33,Sayfa2!$A$1:$C$9998,3,FALSE)) -> yeni [s.] | F33: yeni [s.] | G33: keşfedilmemiş [s.] | H33: değişik [s.] | I33: A2
A34: no | B34: 220 | C34: No | D34: =IF(C34<>"",C34,VLOOKUP(A34,Sayfa2!$A$1:$C$9998,2,FALSE)) -> No | E34: =IF(C34<>"",F34,VLOOKUP(A34,Sayfa2!$A$1:$C$9998,3,FALSE)) -> hayır [ünl.] | F34: hayır [ünl.] | G34: aleyhte oy [i.] | H34: red [i.] | I34: A2
... A43: us | B43: 197 | C43: As | D43: =IF(C43<>"",C43,VLOOKUP(A43,Sayfa2!$A$1:$C$9998,2,FALSE)) -> As | E43: =IF(C43<>"",F43,VLOOKUP(A43,Sayfa2!$A$1:$C$9998,3,FALSE)) -> biz [zm.] | F43: biz [zm.] | G43: abd [i.] | H43: bizi [zm.] | I43: A2
A44: them | B44: 195 | C44: Them | D44: =IF(C44<>"",C44,VLOOKUP(A44,Sayfa2!$A$1:$C$9998,2,FALSE)) -> Them | E44: =IF(C44<>"",F44,VLOOKUP(A44,Sayfa2!$A$1:$C$9998,3,FALSE)) -> onlara [zm.] | F44: onlara [zm.] | G44: onları [zm.] | H44: 0 | I44: A2
A45: than | B45: 194 | C45: Den | D45: =IF(C45<>"",C45,VLOOKUP(A45,Sayfa2!$A$1:$C$9998,2,FALSE)) -> Den | E45: =IF(C45<>"",F45,VLOOKUP(A45,Sayfa2!$A$1:$C$9998,3,FALSE)) -> -den [ed.] | F45: -den [ed.] | G45: hariç [ed.] | H45: -mektense [ed.] | I45: A2
A46: who | B46: 193 | C46: Hu | D46: =IF(C46<>"",C46,VLOOKUP(A46,Sayfa2!$A$1:$C$9998,2,FALSE)) -> Hu | E46: =IF(C46<>"",F46,VLOOKUP(A46,Sayfa2!$A$1:$C$9998,3,FALSE)) -> kimi [zm.] | F46: kimi [zm.] | G46: kim [zm.] | H46: kime [zm.] | I46: A2
A47: really | B47: 184 | C47: Riıli | D47: =IF(C47<>"",C47,VLOOKUP(A47,Sayfa2!$A$1:$C$9998,2,FALSE)) -> Riıli | E47: =IF(C47<>"",F47,VLOOKUP(A47,Sayfa2!$A$1:$C$9998,3,FALSE)) -> hakikaten [zf.] | F47: hakikaten [zf.] | G47: gerçekten [zf.] | H47: cidden [zf.] | I47: A2
A48: good | B48: 182 | C48: Gud | D48: =IF(C48<>"",C48,VLOOKUP(A48,Sayfa2!$A$1:$C$9998,2,FALSE)) -> Gud | E48: =IF(C48<>"",F48,VLOOKUP(A48,Sayfa2!$A$1:$C$9998,3,FALSE)) -> güzel [s.] | F48: güzel [s.] | G48: hayırlı [s.] | H48: iyi [s.] | I48: A1
A49: much | B49: 182 | C49: Maç | D49: =IF(C49<>"",C49,VLOOKUP(A49,Sayfa2!$A$1:$C$9998,2,FALSE)) -> Maç | E49: =IF(C49<>"",F49,VLOOKUP(A49,Sayfa2!$A$1:$C$9998,3,FALSE)) -> fazla [s.] | F49: fazla [s.] | G49: çok [zf.] | H49: çok şey [i.] | I49: A2
A50: after | B50: 173 | C50: aftı | D50: =IF(C50<>"",C50,VLOOKUP(A50,Sayfa2!$A$1:$C$9998,2,FALSE)) -> aftı | E50: =IF(C50<>"",F50,VLOOKUP(A50,Sayfa2!$A$1:$C$9998,3,FALSE)) -> sonra [zf.] | F50: sonra [zf.] | G50: öğleden sonra [i.] | H50: sonra gelen [s.] | I50: A1
A51: because | B51: 172 | C51: Bikoz | D51: =IF(C51<>"",C51,VLOOKUP(A51,Sayfa2!$A$1:$C$9998,2,FALSE)) -> Bikoz | E51: =IF(C51<>"",F51,VLOOKUP(A51,Sayfa2!$A$1:$C$9998,3,FALSE)) -> çünkü [bağ.] | F51: çünkü [bağ.] | G51: -dığı için [bağ.] | H51: zira [bağ.] | I51: A2
A52: got | B52: 172 | C52: Gat | D52: =IF(C52<>"",C52,VLOOKUP(A52,Sayfa2!$A$1:$C$9998,2,FALSE)) -> Gat | E52: =IF(C52<>"",F52,VLOOKUP(A52,Sayfa2!$A$1:$C$9998,3,FALSE)) -> 0 | F52: 0
A53: any | B53: 170 | C53: Eni | D53: =IF(C53<>"",C53,VLOOKUP(A53,Sayfa2!$A$1:$C$9998,2,FALSE)) -> Eni | E53: =IF(C53<>"",F53,VLOOKUP(A53,Sayfa2!$A$1:$C$9998,3,FALSE)) -> lalettayin [s.] | F53: lalettayin [s.] | G53: bazı [s.] | H53: her [s.] | I53: A1
A54: way | B54: 169 | C54: Wey | D54: =IF(C54<>"",C54,VLOOKUP(A54,Sayfa2!$A$1:$C$9998,2,FALSE)) -> Wey | E54: =IF(C54<>"",F54,VLOOKUP(A54,Sayfa2!$A$1:$C$9998,3,FALSE)) -> yol [i.] | F54: yol [i.] | G54: taraf [i.] | H54: tarz [i.] | I54: A2
A55: did | B55: 168 | C55: Did | D55: =IF(C55<>"",C55,VLOOKUP(A55,Sayfa2!$A$1:$C$9998,2,FALSE)) -> Did | E55: =IF(C55<>"",F55,VLOOKUP(A55,Sayfa2!$A$1:$C$9998,3,FALSE)) -> 0 | F55: 0
A56: something | B56: 168 | C56: Samting | D56: =IF(C56<>"",C56,VLOOKUP(A56,Sayfa2!$A$1:$C$9998,2,FALSE)) -> Samting | E56: =IF(C56<>"",F56,VLOOKUP(A56,Sayfa2!$A$1:$C$9998,3,FALSE)) -> bir şey [i.] | F56: bir şey [i.] | G56: falan | H56: 0 | I56: A2
A57: him | B57: 166 | C57: Him | D57: =IF(C57<>"",C57,VLOOKUP(A57,Sayfa2!$A$1:$C$9998,2,FALSE)) -> Him | E57: =IF(C57<>"",F57,VLOOKUP(A57,Sayfa2!$A$1:$C$9998,3,FALSE)) -> ona [zm.] | F57: ona [zm.] | G57: onu [zm.] | H57: (erkek) onu [zm.] | I57: A2
A58: too | B58: 160 | C58: Tuu | D58: =IF(C58<>"",C58,VLOOKUP(A58,Sayfa2!$A$1:$C$9998,2,FALSE)) -> Tuu | E58: =IF(C58<>"",F58,VLOOKUP(A58,Sayfa2!$A$1:$C$9998,3,FALSE)) -> gereğinden çok [s.] | F58: gereğinden çok [s.] | G58: çok [s.] | H58: aşırı [s.] | I58: A2
A59: day | B59: 159 | C59: Dey | D59: =IF(C59<>"",C59,VLOOKUP(A59,Sayfa2!$A$1:$C$9998,2,FALSE)) -> Dey | E59: =IF(C59<>"",F59,VLOOKUP(A59,Sayfa2!$A$1:$C$9998,3,FALSE)) -> gün [i.] | F59: gün [i.] | G59: dönem [i.] | H59: gündüz [i.] | I59: A2
A60: before | B60: 158 | C60: Bifor | D60: =IF(C60<>"",C60,VLOOKUP(A60,Sayfa2!$A$1:$C$9998,2,FALSE)) -> Bifor | E60: =IF(C60<>"",F60,VLOOKUP(A60,Sayfa2!$A$1:$C$9998,3,FALSE)) -> evvel [ed.] | F60: evvel [ed.] | G60: önce [ed.] | H60: daha önce [zf.] | I60: A1
A61: many | B61: 158 | C61: Meni | D61: =IF(C61<>"",C61,VLOOKUP(A61,Sayfa2!$A$1:$C$9998,2,FALSE)) -> Meni | E61: =IF(C61<>"",F61,VLOOKUP(A61,Sayfa2!$A$1:$C$9998,3,FALSE)) -> birçok [s.] | F61: birçok [s.] | G61: çok [zf.] | H61: çoğu [i.] | I61: A2
A62: off | B62: 158 | C62: Of | D62: =IF(C62<>"",C62,VLOOKUP(A62,Sayfa2!$A$1:$C$9998,2,FALSE)) -> Of | E62: =IF(C62<>"",F62,VLOOKUP(A62,Sayfa2!$A$1:$C$9998,3,FALSE)) -> kapalı [s.] | F62: kapalı [s.] | G62: dışında [zf.] | H62: kalkmak [f.] | I62: A2
A63: last | B63: 152 | C63: Lest | D63: =IF(C63<>"",C63,VLOOKUP(A63,Sayfa2!$A$1:$C$9998,2,FALSE)) -> Lest | E63: =IF(C63<>"",F63,VLOOKUP(A63,Sayfa2!$A$1:$C$9998,3,FALSE)) -> sonuncu [s.] | F63: sonuncu [s.] | G63: son [s.] | H63: tutunmak [f.] | I63: A1
A64: say | B64: 147 | C64: Sey | D64: =IF(C64<>"",C64,VLOOKUP(A64,Sayfa2!$A$1:$C$9998,2,FALSE)) -> Sey | E64: =IF(C64<>"",F64,VLOOKUP(A64,Sayfa2!$A$1:$C$9998,3,FALSE)) -> söylemek [f.] | F64: söylemek [f.] | G64: demek [f.] | H64: said - said [f.] | I64: A2
A65: these | B65: 147 | C65: Diz | D65: =IF(C65<>"",C65,VLOOKUP(A65,Sayfa2!$A$1:$C$9998,2,FALSE)) -> Diz | E65: =IF(C65<>"",F65,VLOOKUP(A65,Sayfa2!$A$1:$C$9998,3,FALSE)) -> 0 | F65: 0
A66: please | B66: 142 | C66: Pliiz | D66: =IF(C66<>"",C66,VLOOKUP(A66,Sayfa2!$A$1:$C$9998,2,FALSE)) -> Pliiz | E66: =IF(C66<>"",F66,VLOOKUP(A66,Sayfa2!$A$1:$C$9998,3,FALSE)) -> memnun etmek [f.] | F66: memnun etmek [f.] | G66: lütfen [ünl.] | H66: gönlünü hoş etmek [f.] | I66: A1
A67: said | B67: 142 | C67: Sed | D67: =IF(C67<>"",C67,VLOOKUP(A67,Sayfa2!$A$1:$C$9998,2,FALSE)) -> Sed | E67: =IF(C67<>"",F67,VLOOKUP(A67,Sayfa2!$A$1:$C$9998,3,FALSE)) -> 0 | F67: 0
A68: always | B68: 141 | C68: Olveys | D68: =IF(C68<>"",C68,VLOOKUP(A68,Sayfa2!$A$1:$C$9998,2,FALSE)) -> Olveys | E68: =IF(C68<>"",F68,VLOOKUP(A68,Sayfa2!$A$1:$C$9998,3,FALSE)) -> hep [zf.] | F68: hep [zf.] | G68: her zaman [zf.] | H68: daima [zf.] | I68: A2
A69: most | B69: 141 | C69: Moust | D69: =IF(C69<>"",C69,VLOOKUP(A69,Sayfa2!$A$1:$C$9998,2,FALSE)) -> Moust | E69: =IF(C69<>"",F69,VLOOKUP(A69,Sayfa2!$A$1:$C$9998,3,FALSE)) -> en [s.] | F69: en [s.] | G69: en çok [s.] | H69: en fazlası [i.] | I69: A2
A70: home | B70: 140 | C70: Hom | D70: =IF(C70<>"",C70,VLOOKUP(A70,Sayfa2!$A$1:$C$9998,2,FALSE)) -> Hom | E70: =IF(C70<>"",F70,VLOOKUP(A70,Sayfa2!$A$1:$C$9998,3,FALSE)) -> ev [i.] | F70: ev [i.] | G70: yerleştirmek [f.] | H70: yuvasına dönmek [f.] | I70: A1
A71: job | B71: 140 | C71: Cab | D71: =IF(C71<>"",C71,VLOOKUP(A71,Sayfa2!$A$1:$C$9998,2,FALSE)) -> Cab | E71: =IF(C71<>"",F71,VLOOKUP(A71,Sayfa2!$A$1:$C$9998,3,FALSE)) -> görev [i.] | F71: görev [i.] | G71: iş [i.] | H71: kiraya vermek [f.] | I71: A2
A72: lot | B72: 138 | C72: Lot | D72: =IF(C72<>"",C72,VLOOKUP(A72,Sayfa2!$A$1:$C$9998,2,FALSE)) -> Lot | E72: =IF(C72<>"",F72,VLOOKUP(A72,Sayfa2!$A$1:$C$9998,3,FALSE)) -> pay [i.] | F72: pay [i.] | G72: bölüştürmek [f.] | H72: taksim etmek [f.] | I72: A2
A73: feel | B73: 137 | C73: Fiil | D73: =IF(C73<>"",C73,VLOOKUP(A73,Sayfa2!$A$1:$C$9998,2,FALSE)) -> Fiil | E73: =IF(C73<>"",F73,VLOOKUP(A73,Sayfa2!$A$1:$C$9998,3,FALSE)) -> hissetmek [f.] | F73: hissetmek [f.] | G73: felt - felt [f.] | H73: sezmek [f.] | I73: A2
A74: never | B74: 137 | C74: Never | D74: =IF(C74<>"",C74,VLOOKUP(A74,Sayfa2!$A$1:$C$9998,2,FALSE)) -> Never | E74: =IF(C74<>"",F74,VLOOKUP(A74,Sayfa2!$A$1:$C$9998,3,FALSE)) -> hiç [zf.] | F74: hiç [zf.] | G74: asla [ünl.] | H74: katiyen [zf.] | I74: A2
A75: other | B75: 137 | C75: Adır | D75: =IF(C75<>"",C75,VLOOKUP(A75,Sayfa2!$A$1:$C$9998,2,FALSE)) -> Adır | E75: =IF(C75<>"",F75,VLOOKUP(A75,Sayfa2!$A$1:$C$9998,3,FALSE)) -> öbür [s.] | F75: öbür [s.] | G75: öteki [s.] | H75: başka [s.] | I75: A2
A76: case | B76: 136 | C76: Keys | D76: =IF(C76<>"",C76,VLOOKUP(A76,Sayfa2!$A$1:$C$9998,2,FALSE)) -> Keys | E76: =IF(C76<>"",F76,VLOOKUP(A76,Sayfa2!$A$1:$C$9998,3,FALSE)) -> dava [i.] | F76: dava [i.] | G76: kasa [i.] | H76: kılıf [i.] | I76: A1
A77: year | B77: 134 | C77: Yiır | D77: =IF(C77<>"",C77,VLOOKUP(A77,Sayfa2!$A$1:$C$9998,2,FALSE)) -> Yiır | E77: =IF(C77<>"",F77,VLOOKUP(A77,Sayfa2!$A$1:$C$9998,3,FALSE)) -> yıl [i.] | F77: yıl [i.] | G77: sene [i.] | H77: ihtiyarlık [i.] | I77: A2
A78: love | B78: 133 | C78: Lav | D78: =IF(C78<>"",C78,VLOOKUP(A78,Sayfa2!$A$1:$C$9998,2,FALSE)) -> Lav | E78: =IF(C78<>"",F78,VLOOKUP(A78,Sayfa2!$A$1:$C$9998,3,FALSE)) -> sevmek [f.] | F78: sevmek [f.] | G78: sevda [i.] | H78: aşk [i.] | I78: A2
A79: over | B79: 132 | C79: Ouvır | D79: =IF(C79<>"",C79,VLOOKUP(A79,Sayfa2!$A$1:$C$9998,2,FALSE)) -> Ouvır | E79: =IF(C79<>"",F79,VLOOKUP(A79,Sayfa2!$A$1:$C$9998,3,FALSE)) -> bitmiş [s.] | F79: bitmiş [s.] | G79: üzerine [ed.] | H79: üstüne [ed.] | I79: A2
A80: years | B80: 132 | C80: Yirz | D80: =IF(C80<>"",C80,VLOOKUP(A80,Sayfa2!$A$1:$C$9998,2,FALSE)) -> Yirz | E80: =IF(C80<>"",F80,VLOOKUP(A80,Sayfa2!$A$1:$C$9998,3,FALSE)) -> 0 | F80: 0
A81: help | B81: 128 | C81: Help | D81: =IF(C81<>"",C81,VLOOKUP(A81,Sayfa2!$A$1:$C$9998,2,FALSE)) -> Help | E81: =IF(C81<>"",F81,VLOOKUP(A81,Sayfa2!$A$1:$C$9998,3,FALSE)) -> yardım etmek [f.] | F81: yardım etmek [f.] | G81: yardım [i.] | H81: muavenet etmek [f.] | I81: A2
A82: every | B82: 127 | C82: Evri | D82: =IF(C82<>"",C82,VLOOKUP(A82,Sayfa2!$A$1:$C$9998,2,FALSE)) -> Evri | E82: =IF(C82<>"",F82,VLOOKUP(A82,Sayfa2!$A$1:$C$9998,3,FALSE)) -> her [s.] | F82: her [s.] | G82: bütün [s.] | H82: alışılmış [s.] | I82: A2
A83: right | B83: 126 | C83: Rayt | D83: =IF(C83<>"",C83,VLOOKUP(A83,Sayfa2!$A$1:$C$9998,2,FALSE)) -> Rayt | E83: =IF(C83<>"",F83,VLOOKUP(A83,Sayfa2!$A$1:$C$9998,3,FALSE)) -> sağ [i.] | F83: sağ [i.] | G83: hak [i.] | H83: haklı [s.] | I83: A2
A84: life | B84: 124 | C84: Layf | D84: =IF(C84<>"",C84,VLOOKUP(A84,Sayfa2!$A$1:$C$9998,2,FALSE)) -> Layf | E84: =IF(C84<>"",F84,VLOOKUP(A84,Sayfa2!$A$1:$C$9998,3,FALSE)) -> yaşam [i.] | F84: yaşam [i.] | G84: hayat [i.] | H84: can [i.] | I84: A2
A85: better | B85: 121 | C85: Better | D85: =IF(C85<>"",C85,VLOOKUP(A85,Sayfa2!$A$1:$C$9998,2,FALSE)) -> Better | E85: =IF(C85<>"",F85,VLOOKUP(A85,Sayfa2!$A$1:$C$9998,3,FALSE)) -> daha iyi [s.] | F85: daha iyi [s.] | G85: iyileştirmek [f.] | H85: ıslah etmek [f.] | I85: A1
A86: money | B86: 121 | C86: Mani | D86: =IF(C86<>"",C86,VLOOKUP(A86,Sayfa2!$A$1:$C$9998,2,FALSE)) -> Mani | E86: =IF(C86<>"",F86,VLOOKUP(A86,Sayfa2!$A$1:$C$9998,3,FALSE)) -> para [i.] | F86: para [i.] | G86: para kırmak [f.] | H86: patpat [i.] | I86: A2
A87: able | B87: 119 | C87: Eybıl | D87: =IF(C87<>"",C87,VLOOKUP(A87,Sayfa2!$A$1:$C$9998,2,FALSE)) -> Eybıl | E87: =IF(C87<>"",F87,VLOOKUP(A87,Sayfa2!$A$1:$C$9998,3,FALSE)) -> hünerli [s.] | F87: hünerli [s.] | G87: kadir [s.] | H87: gücü yeten [s.] | I87: A1
A88: come | B88: 119 | C88: Kam | D88: =IF(C88<>"",C88,VLOOKUP(A88,Sayfa2!$A$1:$C$9998,2,FALSE)) -> Kam | E88: =IF(C88<>"",F88,VLOOKUP(A88,Sayfa2!$A$1:$C$9998,3,FALSE)) -> gelmek [f.] | F88: gelmek [f.] | G88: came - come [f.] | H88: gelip dayanmak [f.] | I88: A2
A89: working | B89: 119 | C89: Vörking | D89: =IF(C89<>"",C89,VLOOKUP(A89,Sayfa2!$A$1:$C$9998,2,FALSE)) -> Vörking | E89: =IF(C89<>"",F89,VLOOKUP(A89,Sayfa2!$A$1:$C$9998,3,FALSE)) -> çalışma [i.] | F89: çalışma [i.] | G89: işleme tarzı [i.] | H89: temel [i.] | I89: A1
A90: first | B90: 118 | C90: Först | D90: =IF(C90<>"",C90,VLOOKUP(A90,Sayfa2!$A$1:$C$9998,2,FALSE)) -> Först | E90: =IF(C90<>"",F90,VLOOKUP(A90,Sayfa2!$A$1:$C$9998,3,FALSE)) -> birinci [s.] | F90: birinci [s.] | G90: ilk [s.] | H90: önce [zf.] | I90: A1
A91: food | B91: 117 | C91: Fuud | D91: =IF(C91<>"",C91,VLOOKUP(A91,Sayfa2!$A$1:$C$9998,2,FALSE)) -> Fuud | E91: =IF(C91<>"",F91,VLOOKUP(A91,Sayfa2!$A$1:$C$9998,3,FALSE)) -> besin [i.] | F91: besin [i.] | G91: yiyecek [i.] | H91: gıda [i.] | I91: A2
A92: well | B92: 117 | C92: Wel | D92: =IF(C92<>"",C92,VLOOKUP(A92,Sayfa2!$A$1:$C$9998,2,FALSE)) -> Wel | E92: =IF(C92<>"",F92,VLOOKUP(A92,Sayfa2!$A$1:$C$9998,3,FALSE)) -> fışkırmak [f.] | F92: fışkırmak [f.] | G92: kuyu [i.] | H92: iyi [s.] | I92: A2
A93: also | B93: 116 | C93: Olso | D93: =IF(C93<>"",C93,VLOOKUP(A93,Sayfa2!$A$1:$C$9998,2,FALSE)) -> Olso | E93: =IF(C93<>"",F93,VLOOKUP(A93,Sayfa2!$A$1:$C$9998,3,FALSE)) -> ayrıca [zf.] | F93: ayrıca [zf.] | G93: yine [zf.] | H93: da [zf.] | I93: A2
A94: made | B94: 116 | C94: Meyd | D94: =IF(C94<>"",C94,VLOOKUP(A94,Sayfa2!$A$1:$C$9998,2,FALSE)) -> Meyd | E94: =IF(C94<>"",F94,VLOOKUP(A94,Sayfa2!$A$1:$C$9998,3,FALSE)) -> 0 | F94: 0
A95: give | B95: 115 | C95: Giv | D95: =IF(C95<>"",C95,VLOOKUP(A95,Sayfa2!$A$1:$C$9998,2,FALSE)) -> Giv | E95: =IF(C95<>"",F95,VLOOKUP(A95,Sayfa2!$A$1:$C$9998,3,FALSE)) -> vermek [f.] | F95: vermek [f.] | G95: gave - given [f.] | H95: bahşetmek [f.] | I95: A2
A96: keep | B96: 112 | C96: Kiip | D96: =IF(C96<>"",C96,VLOOKUP(A96,Sayfa2!$A$1:$C$9998,2,FALSE)) -> Kiip | E96: =IF(C96<>"",F96,VLOOKUP(A96,Sayfa2!$A$1:$C$9998,3,FALSE)) -> tutmak [f.] | F96: tutmak [f.] | G96: saklamak [f.] | H96: kept - kept [f.] | I96: A2
A97: back | B97: 111 | C97: Bek | D97: =IF(C97<>"",C97,VLOOKUP(A97,Sayfa2!$A$1:$C$9998,2,FALSE)) -> Bek | E97: =IF(C97<>"",F97,VLOOKUP(A97,Sayfa2!$A$1:$C$9998,3,FALSE)) -> art [i.] | F97: art [i.] | G97: arkalık [i.] | H97: sırt [i.] | I97: A1
A98: only | B98: 111 | C98: Ounli | D98: =IF(C98<>"",C98,VLOOKUP(A98,Sayfa2!$A$1:$C$9998,2,FALSE)) -> Ounli | E98: =IF(C98<>"",F98,VLOOKUP(A98,Sayfa2!$A$1:$C$9998,3,FALSE)) -> tek [s.] | F98: tek [s.] | G98: sırf [zf.] | H98: yalnızca [zf.] | I98: A2
A99: even | B99: 110 | C99: İvın | D99: =IF(C99<>"",C99,VLOOKUP(A99,Sayfa2!$A$1:$C$9998,2,FALSE)) -> İvın | E99: =IF(C99<>"",F99,VLOOKUP(A99,Sayfa2!$A$1:$C$9998,3,FALSE)) -> düzgün [s.] | F99: düzgün [s.] | G99: düz [s.] | H99: pürüzsüz [s.] | I99: A2
A100: someone | B100: 110 | C100: Samwan | D100: =IF(C100<>"",C100,VLOOKUP(A100,Sayfa2!$A$1:$C$9998,2,FALSE)) -> Samwan | E100: =IF(C100<>"",F100,VLOOKUP(A100,Sayfa2!$A$1:$C$9998,3,FALSE)) -> birisi [zm.] | F100: birisi [zm.] | G100: kimse [zm.] | H100: bir kimse [zm.] | I100: A2
A101: let | B101: 108 | C101: Let | D101: =IF(C101<>"",C101,VLOOKUP(A101,Sayfa2!$A$1:$C$9998,2,FALSE)) -> Let | E101: =IF(C101<>"",F101,VLOOKUP(A101,Sayfa2!$A$1:$C$9998,3,FALSE)) -> izin vermek [f.] | F101: izin vermek [f.] | G101: let - let [f.] | H101: vermek [f.] | I101: A2
A102: didn't | B102: 107 | C102: Didınt | D102: =IF(C102<>"",C102,VLOOKUP(A102,Sayfa2!$A$1:$C$9998,2,FALSE)) -> Didınt | E102: =IF(C102<>"",F102,VLOOKUP(A102,Sayfa2!$A$1:$C$9998,3,FALSE)) -> 0 | F102: 0
A103: long | B103: 107 | C103: Long | D103: =IF(C103<>"",C103,VLOOKUP(A103,Sayfa2!$A$1:$C$9998,2,FALSE)) -> Long | E103: =IF(C103<>"",F103,VLOOKUP(A103,Sayfa2!$A$1:$C$9998,3,FALSE)) -> uzun [s.] | F103: uzun [s.] | G103: hasretini çekmek [f.] | H103: susamak [f.] | I103: A2
A104: next | B104: 107 | C104: Nekst | D104: =IF(C104<>"",C104,VLOOKUP(A104,Sayfa2!$A$1:$C$9998,2,FALSE)) -> Nekst | E104: =IF(C104<>"",F104,VLOOKUP(A104,Sayfa2!$A$1:$C$9998,3,FALSE)) -> sonraki [ed.] | F104: sonraki [ed.] | G104: bundan sonraki [s.] | H104: en bitişik [s.] | I104: A2
A105: such | B105: 106 | C105: Saç | D105: =IF(C105<>"",C105,VLOOKUP(A105,Sayfa2!$A$1:$C$9998,2,FALSE)) -> Saç | E105: =IF(C105<>"",F105,VLOOKUP(A105,Sayfa2!$A$1:$C$9998,3,FALSE)) -> çok [s.] | F105: çok [s.] | G105: böylesine [s.] | H105: bu gibi [s.] | I105: A1
A106: great | B106: 104 | C106: Greyt | D106: =IF(C106<>"",C106,VLOOKUP(A106,Sayfa2!$A$1:$C$9998,2,FALSE)) -> Greyt | E106: =IF(C106<>"",F106,VLOOKUP(A106,Sayfa2!$A$1:$C$9998,3,FALSE)) -> mükemmel [s.] | F106: mükemmel [s.] | G106: müthiş [s.] | H106: harika [s.] | I106: A2
A107: down | B107: 103 | C107: Daun | D107: =IF(C107<>"",C107,VLOOKUP(A107,Sayfa2!$A$1:$C$9998,2,FALSE)) -> Daun | E107: =IF(C107<>"",F107,VLOOKUP(A107,Sayfa2!$A$1:$C$9998,3,FALSE)) -> aşağıya doğru [zf.] | F107: aşağıya doğru [zf.] | G107: aşağı [ed.] | H107: alaşağı etmek [f.] | I107: A2
A108: meeting | B108: 103 | C108: Miiting | D108: =IF(C108<>"",C108,VLOOKUP(A108,Sayfa2!$A$1:$C$9998,2,FALSE)) -> Miiting | E108: =IF(C108<>"",F108,VLOOKUP(A108,Sayfa2!$A$1:$C$9998,3,FALSE)) -> toplantı [i.] | F108: toplantı [i.] | G108: buluşma [i.] | H108: miting [i.] | I108: A2
...

Sheet Sayfa2
A1: İngilizce | B1: Türkçe Okunuş | C1: Türkçe Anlam
A2: had | B2: Hed | C2: sahipti
A3: got | B3: Gat | C3: aldı / oldu
A4: did | B4: Did | C4: yaptı
A5: these | B5: Diz | C5: bunlar
A6: said | B6: Sed | C6: söyledi
A7: years | B7: Yirz | C7: yıllar
A8: made | B8: Meyd | C8: yaptı
A9: didn't | B9: Didınt | C9: yapmadı
A10: things | B10: Tings | C10: şeyler
A11: that's | B11: Dets | C11: o / şu
A12: ended | B12: Endid | C12: sona erdi
... A2285: letters | B2285: Letırz | C2285: harfler / mektuplar
A2286: lgbt | B2286: El ci bi ti | C2286: LGBT (lezbiyen | D2286: gey | E2286: biseksüel | F2286: trans)
A2287: libraries | B2287: Laybrəriz | C2287: kütüphaneler
A2288: lied | B2288: Layd | C2288: yalan söyledi
A2289: lifesaver | B2289: Layfseyvır | C2289: cankurtaran (hayat kurtaran)
A2290: lifestyles | B2290: Layfstayls | C2290: yaşam tarzları
A2291: liffey | B2291: Lifi | C2291: Liffey (nehir)
A2292: lifts | B2292: Lifts | C2292: kaldırır / asansörler
A2293: limits | B2293: Limits | C2293: sınırlar
A2294: linda | B2294: Lində | C2294: Linda (isim)
A2295: liquids | B2295: Likvits | C2295: sıvılar
A2296: lobster | B2296: Labstır | C2296: ıstakoz
A2297: locally | B2297: Lokəli | C2297: yerel olarak
A2298: locking | B2298: Lokin | C2298: kilitleme
... A2421: peope | B2421: Pipl | C2421: insanlar (yanlış yazım: people)
A2422: performances | B2422: P
A2423: careers | B2423: Kariyırz | C2423: kariyerler
A2424: carnivores | B2424: Karnivors | C2424: etoburlar
A2425: casuals | B2425: Kazuıls | C2425: gündelik şeyler / sıradanlar
A2426: cat's | B2426: Kets | C2426: kedinin
A2427: categorize | B2427: Ketıgorayz | C2427: kategorilere ayırmak
A2428: caterer | B2428: Keytırır | C2428: yemek servisi yapan kişi / kurum
A2429: catering | B2429: Keytiring | C2429: yemek servisi / catering
A2430: cath | B2430: Keth | C2430: Kath (isim kısaltması)
A2431: cellphone | B2431: Selfovn | C2431: cep telefonu
A2432: ceo | B2432: Si i ov | C2432: CEO (genel müdür)
A2433: ceramic | B2433: Sıremik | C2433: seramik
A2434: cfo | B2434: Si ef ov | C2434: CFO (finans müdürü)
... A2848: letters | B2848: Letırz | C2848: harfler / mektuplar
A2849: lgbt | B2849: El ci bi ti | C2849: LGBT (lezbiyen | D2849: gey | E2849: biseksüel | F2849: trans)
A2850: libraries | B2850: Laybrəriz | C2850: kütüphaneler
A2851: lied | B2851: Layd | C2851: yalan söyledi
A2852: lifesaver | B2852: Layfseyvır | C2852: cankurtaran (hayat kurtaran)
A2853: lifestyles | B2853: Layfstayls | C2853: yaşam tarzları
A2854: liffey | B2854: Lifi | C2854: Liffey (nehir)
A2855: lifts | B2855: Lifts | C2855: kaldırır / asansörler
A2856: limits | B2856: Limits | C2856: sınırlar
A2857: linda | B2857: Lində | C2857: Linda (isim)
A2858: liquids | B2858: Likvits | C2858: sıvılar
A2859: lobster | B2859: Labstır | C2859: ıstakoz
A2860: locally | B2860: Lokəli | C2860: yerel olarak
A2861: locking | B2861: Lokin | C2861: kilitleme
... A3652: boosted | B3652: Bustid | C3652: yükseltildi / artırıldı
A3653: booth | B3653: Bu | C3653: t | D3653: kabin / kulübe
A3654: booths | B3654: Buths | C3654: kabinler / kulübeler
A3655: bosses | B3655: Bosız | C3655: patronlar
A3656: bossy | B3656: Bosi | C3656: otoriter / patronluk taslayan
A3657: botanical | B3657: Botənıkıl | C3657: botanik
A3658: botin | B3658: Botin | C3658: botin (Türkçe isim)
A3659: bottled | B3659: Botıld | C3659: şişelenmiş
A3660: bottoms | B3660: Botımz | C3660: dip / alt kısımlar
A3661: boxer | B3661: Baksır | C3661: boksör
A3662: boxes | B3662: Baksız | C3662: kutular
A3663: boycott | B3663: Boykot | C3663: boykot
A3664: boycotted | B3664: Boykotid | C3664: boykot edildi
A3665: boyfriend's | B3665: Boyfrendz | C3665: erkek arkadaşın
... A3903: concepts | B3903: Konsepts | C3903: kavramlar
A3904: concerning
A3905: abbreviation | B3905: Abriyiviyeyşın | C3905: kısaltma
A3906: abide | B3906: Ebayd | C3906: bağlı kalmak / katlanmak
A3907: abnormalities | B3907: Abnormələtiz | C3907: anormallikler
A3908: aboard | B3908: Ebord | C3908: gemide / uçakta / trende
A3909: abondon | B3909: Ebandın | C3909: terk etmek (yanlış yazım: abandon)
A3910: abraham | B3910: Ebırahım | C3910: Abraham (isim)
A3911: abuses | B3911: Ebyuzız | C3911: kötüye kullanımlar / istismarlar
A3912: academy's | B3912: Əkademiz | C3912: akademinin
A3913: accelerated | B3913: Əkseləreytid | C3913: hızlandırıldı
A3914: accessed | B3914: Əksest | C3914: erişildi
A3915: accidental | B3915: Əksidentəl | C3915: kazara
A3916: accompanied | B3916: Əkampənid | C3916: eşlik edildi
... A4203: boosted | B4203: Bustid | C4203: yükseltildi / artırıldı
A4204: booth | B4204: Bu | C4204: t | D4204: kabin / kulübe
A4205: booths | B4205: Buths | C4205: kabinler / kulübeler
A4206: bosses | B4206: Bosız | C4206: patronlar
A4207: bossy | B4207: Bosi | C4207: otoriter / patronluk taslayan
A4208: botanical | B4208: Botənıkıl | C4208: botanik
A4209: botin | B4209: Botin | C4209: botin (Türkçe isim)
A4210: bottled | B4210: Botıld | C4210: şişelenmiş
A4211: bottoms | B4211: Botımz | C4211: dip / alt kısımlar
A4212: boxer | B4212: Baksır | C4212: boksör
A4213: boxes | B4213: Baksız | C4213: kutular
A4214: boycott | B4214: Boykot | C4214: boykot
A4215: boycotted | B4215: Boykotid | C4215: boykot edildi
A4216: boyfriend's | B4216: Boyfrendz | C4216: erkek arkadaşın
... A6849: zoom | B6849: Zum | C6849: zoom (yakınlaştırmak / uzaklaştırmak)
